{
  "id": "7f14dbfa-6415-4572-960f-eb2598ce4dbc",
  "prevId": "00000000-0000-0000-0000-000000000000",
  "version": "7",
  "dialect": "postgresql",
  "tables": {
    "public.ai_jobs": {
      "name": "ai_jobs",
      "schema": "",
      "columns": {
        "id": {
          "name": "id",
          "type": "uuid",
          "primaryKey": true,
          "notNull": true,
          "default": "gen_random_uuid()"
        },
        "organization_id": {
          "name": "organization_id",
          "type": "uuid",
          "primaryKey": false,
          "notNull": true
        },
        "patient_id": {
          "name": "patient_id",
          "type": "uuid",
          "primaryKey": false,
          "notNull": false
        },
        "visit_id": {
          "name": "visit_id",
          "type": "uuid",
          "primaryKey": false,
          "notNull": false
        },
        "kind": {
          "name": "kind",
          "type": "ai_job_kind",
          "typeSchema": "public",
          "primaryKey": false,
          "notNull": true
        },
        "status": {
          "name": "status",
          "type": "ai_job_status",
          "typeSchema": "public",
          "primaryKey": false,
          "notNull": true,
          "default": "'queued'"
        },
        "input_storage_path": {
          "name": "input_storage_path",
          "type": "text",
          "primaryKey": false,
          "notNull": false
        },
        "output_text": {
          "name": "output_text",
          "type": "text",
          "primaryKey": false,
          "notNull": false
        },
        "model_name": {
          "name": "model_name",
          "type": "text",
          "primaryKey": false,
          "notNull": false
        },
        "created_at": {
          "name": "created_at",
          "type": "timestamp with time zone",
          "primaryKey": false,
          "notNull": true,
          "default": "now()"
        },
        "reviewed_at": {
          "name": "reviewed_at",
          "type": "timestamp with time zone",
          "primaryKey": false,
          "notNull": false
        }
      },
      "indexes": {},
      "foreignKeys": {
        "ai_jobs_organization_id_organizations_id_fk": {
          "name": "ai_jobs_organization_id_organizations_id_fk",
          "tableFrom": "ai_jobs",
          "tableTo": "organizations",
          "columnsFrom": [
            "organization_id"
          ],
          "columnsTo": [
            "id"
          ],
          "onDelete": "no action",
          "onUpdate": "no action"
        },
        "ai_jobs_patient_id_patients_id_fk": {
          "name": "ai_jobs_patient_id_patients_id_fk",
          "tableFrom": "ai_jobs",
          "tableTo": "patients",
          "columnsFrom": [
            "patient_id"
          ],
          "columnsTo": [
            "id"
          ],
          "onDelete": "no action",
          "onUpdate": "no action"
        },
        "ai_jobs_visit_id_visits_id_fk": {
          "name": "ai_jobs_visit_id_visits_id_fk",
          "tableFrom": "ai_jobs",
          "tableTo": "visits",
          "columnsFrom": [
            "visit_id"
          ],
          "columnsTo": [
            "id"
          ],
          "onDelete": "no action",
          "onUpdate": "no action"
        }
      },
      "compositePrimaryKeys": {},
      "uniqueConstraints": {},
      "policies": {},
      "checkConstraints": {},
      "isRLSEnabled": false
    },
    "public.appointments": {
      "name": "appointments",
      "schema": "",
      "columns": {
        "id": {
          "name": "id",
          "type": "uuid",
          "primaryKey": true,
          "notNull": true,
          "default": "gen_random_uuid()"
        },
        "organization_id": {
          "name": "organization_id",
          "type": "uuid",
          "primaryKey": false,
          "notNull": true
        },
        "patient_id": {
          "name": "patient_id",
          "type": "uuid",
          "primaryKey": false,
          "notNull": false
        },
        "doctor_user_id": {
          "name": "doctor_user_id",
          "type": "uuid",
          "primaryKey": false,
          "notNull": false
        },
        "chair_id": {
          "name": "chair_id",
          "type": "uuid",
          "primaryKey": false,
          "notNull": false
        },
        "status": {
          "name": "status",
          "type": "appointment_status",
          "typeSchema": "public",
          "primaryKey": false,
          "notNull": true,
          "default": "'planned'"
        },
        "starts_at": {
          "name": "starts_at",
          "type": "timestamp with time zone",
          "primaryKey": false,
          "notNull": true
        },
        "ends_at": {
          "name": "ends_at",
          "type": "timestamp with time zone",
          "primaryKey": false,
          "notNull": true
        },
        "reason": {
          "name": "reason",
          "type": "text",
          "primaryKey": false,
          "notNull": false
        },
        "comment": {
          "name": "comment",
          "type": "text",
          "primaryKey": false,
          "notNull": false
        }
      },
      "indexes": {},
      "foreignKeys": {
        "appointments_organization_id_organizations_id_fk": {
          "name": "appointments_organization_id_organizations_id_fk",
          "tableFrom": "appointments",
          "tableTo": "organizations",
          "columnsFrom": [
            "organization_id"
          ],
          "columnsTo": [
            "id"
          ],
          "onDelete": "no action",
          "onUpdate": "no action"
        },
        "appointments_patient_id_patients_id_fk": {
          "name": "appointments_patient_id_patients_id_fk",
          "tableFrom": "appointments",
          "tableTo": "patients",
          "columnsFrom": [
            "patient_id"
          ],
          "columnsTo": [
            "id"
          ],
          "onDelete": "no action",
          "onUpdate": "no action"
        },
        "appointments_doctor_user_id_users_id_fk": {
          "name": "appointments_doctor_user_id_users_id_fk",
          "tableFrom": "appointments",
          "tableTo": "users",
          "columnsFrom": [
            "doctor_user_id"
          ],
          "columnsTo": [
            "id"
          ],
          "onDelete": "no action",
          "onUpdate": "no action"
        },
        "appointments_chair_id_chairs_id_fk": {
          "name": "appointments_chair_id_chairs_id_fk",
          "tableFrom": "appointments",
          "tableTo": "chairs",
          "columnsFrom": [
            "chair_id"
          ],
          "columnsTo": [
            "id"
          ],
          "onDelete": "no action",
          "onUpdate": "no action"
        }
      },
      "compositePrimaryKeys": {},
      "uniqueConstraints": {},
      "policies": {},
      "checkConstraints": {},
      "isRLSEnabled": false
    },
    "public.attachments": {
      "name": "attachments",
      "schema": "",
      "columns": {
        "id": {
          "name": "id",
          "type": "uuid",
          "primaryKey": true,
          "notNull": true,
          "default": "gen_random_uuid()"
        },
        "organization_id": {
          "name": "organization_id",
          "type": "uuid",
          "primaryKey": false,
          "notNull": true
        },
        "patient_id": {
          "name": "patient_id",
          "type": "uuid",
          "primaryKey": false,
          "notNull": false
        },
        "visit_id": {
          "name": "visit_id",
          "type": "uuid",
          "primaryKey": false,
          "notNull": false
        },
        "file_name": {
          "name": "file_name",
          "type": "text",
          "primaryKey": false,
          "notNull": true
        },
        "mime_type": {
          "name": "mime_type",
          "type": "text",
          "primaryKey": false,
          "notNull": true
        },
        "storage_path": {
          "name": "storage_path",
          "type": "text",
          "primaryKey": false,
          "notNull": true
        },
        "sha256": {
          "name": "sha256",
          "type": "text",
          "primaryKey": false,
          "notNull": true
        },
        "created_at": {
          "name": "created_at",
          "type": "timestamp with time zone",
          "primaryKey": false,
          "notNull": true,
          "default": "now()"
        }
      },
      "indexes": {},
      "foreignKeys": {
        "attachments_organization_id_organizations_id_fk": {
          "name": "attachments_organization_id_organizations_id_fk",
          "tableFrom": "attachments",
          "tableTo": "organizations",
          "columnsFrom": [
            "organization_id"
          ],
          "columnsTo": [
            "id"
          ],
          "onDelete": "no action",
          "onUpdate": "no action"
        },
        "attachments_patient_id_patients_id_fk": {
          "name": "attachments_patient_id_patients_id_fk",
          "tableFrom": "attachments",
          "tableTo": "patients",
          "columnsFrom": [
            "patient_id"
          ],
          "columnsTo": [
            "id"
          ],
          "onDelete": "no action",
          "onUpdate": "no action"
        },
        "attachments_visit_id_visits_id_fk": {
          "name": "attachments_visit_id_visits_id_fk",
          "tableFrom": "attachments",
          "tableTo": "visits",
          "columnsFrom": [
            "visit_id"
          ],
          "columnsTo": [
            "id"
          ],
          "onDelete": "no action",
          "onUpdate": "no action"
        }
      },
      "compositePrimaryKeys": {},
      "uniqueConstraints": {},
      "policies": {},
      "checkConstraints": {},
      "isRLSEnabled": false
    },
    "public.audit_events": {
      "name": "audit_events",
      "schema": "",
      "columns": {
        "id": {
          "name": "id",
          "type": "uuid",
          "primaryKey": true,
          "notNull": true,
          "default": "gen_random_uuid()"
        },
        "organization_id": {
          "name": "organization_id",
          "type": "uuid",
          "primaryKey": false,
          "notNull": true
        },
        "actor_user_id": {
          "name": "actor_user_id",
          "type": "uuid",
          "primaryKey": false,
          "notNull": false
        },
        "entity_type": {
          "name": "entity_type",
          "type": "text",
          "primaryKey": false,
          "notNull": true
        },
        "entity_id": {
          "name": "entity_id",
          "type": "uuid",
          "primaryKey": false,
          "notNull": true
        },
        "action": {
          "name": "action",
          "type": "text",
          "primaryKey": false,
          "notNull": true
        },
        "reason": {
          "name": "reason",
          "type": "text",
          "primaryKey": false,
          "notNull": false
        },
        "created_at": {
          "name": "created_at",
          "type": "timestamp with time zone",
          "primaryKey": false,
          "notNull": true,
          "default": "now()"
        }
      },
      "indexes": {},
      "foreignKeys": {
        "audit_events_organization_id_organizations_id_fk": {
          "name": "audit_events_organization_id_organizations_id_fk",
          "tableFrom": "audit_events",
          "tableTo": "organizations",
          "columnsFrom": [
            "organization_id"
          ],
          "columnsTo": [
            "id"
          ],
          "onDelete": "no action",
          "onUpdate": "no action"
        },
        "audit_events_actor_user_id_users_id_fk": {
          "name": "audit_events_actor_user_id_users_id_fk",
          "tableFrom": "audit_events",
          "tableTo": "users",
          "columnsFrom": [
            "actor_user_id"
          ],
          "columnsTo": [
            "id"
          ],
          "onDelete": "no action",
          "onUpdate": "no action"
        }
      },
      "compositePrimaryKeys": {},
      "uniqueConstraints": {},
      "policies": {},
      "checkConstraints": {},
      "isRLSEnabled": false
    },
    "public.chairs": {
      "name": "chairs",
      "schema": "",
      "columns": {
        "id": {
          "name": "id",
          "type": "uuid",
          "primaryKey": true,
          "notNull": true,
          "default": "gen_random_uuid()"
        },
        "organization_id": {
          "name": "organization_id",
          "type": "uuid",
          "primaryKey": false,
          "notNull": true
        },
        "clinic_id": {
          "name": "clinic_id",
          "type": "uuid",
          "primaryKey": false,
          "notNull": true
        },
        "name": {
          "name": "name",
          "type": "text",
          "primaryKey": false,
          "notNull": true
        },
        "is_active": {
          "name": "is_active",
          "type": "boolean",
          "primaryKey": false,
          "notNull": true,
          "default": true
        }
      },
      "indexes": {},
      "foreignKeys": {
        "chairs_organization_id_organizations_id_fk": {
          "name": "chairs_organization_id_organizations_id_fk",
          "tableFrom": "chairs",
          "tableTo": "organizations",
          "columnsFrom": [
            "organization_id"
          ],
          "columnsTo": [
            "id"
          ],
          "onDelete": "no action",
          "onUpdate": "no action"
        },
        "chairs_clinic_id_clinics_id_fk": {
          "name": "chairs_clinic_id_clinics_id_fk",
          "tableFrom": "chairs",
          "tableTo": "clinics",
          "columnsFrom": [
            "clinic_id"
          ],
          "columnsTo": [
            "id"
          ],
          "onDelete": "no action",
          "onUpdate": "no action"
        }
      },
      "compositePrimaryKeys": {},
      "uniqueConstraints": {},
      "policies": {},
      "checkConstraints": {},
      "isRLSEnabled": false
    },
    "public.clinics": {
      "name": "clinics",
      "schema": "",
      "columns": {
        "id": {
          "name": "id",
          "type": "uuid",
          "primaryKey": true,
          "notNull": true,
          "default": "gen_random_uuid()"
        },
        "organization_id": {
          "name": "organization_id",
          "type": "uuid",
          "primaryKey": false,
          "notNull": true
        },
        "name": {
          "name": "name",
          "type": "text",
          "primaryKey": false,
          "notNull": true
        },
        "address": {
          "name": "address",
          "type": "text",
          "primaryKey": false,
          "notNull": false
        },
        "phone": {
          "name": "phone",
          "type": "text",
          "primaryKey": false,
          "notNull": false
        },
        "timezone": {
          "name": "timezone",
          "type": "text",
          "primaryKey": false,
          "notNull": true,
          "default": "'Europe/Samara'"
        },
        "created_at": {
          "name": "created_at",
          "type": "timestamp with time zone",
          "primaryKey": false,
          "notNull": true,
          "default": "now()"
        }
      },
      "indexes": {},
      "foreignKeys": {
        "clinics_organization_id_organizations_id_fk": {
          "name": "clinics_organization_id_organizations_id_fk",
          "tableFrom": "clinics",
          "tableTo": "organizations",
          "columnsFrom": [
            "organization_id"
          ],
          "columnsTo": [
            "id"
          ],
          "onDelete": "no action",
          "onUpdate": "no action"
        }
      },
      "compositePrimaryKeys": {},
      "uniqueConstraints": {},
      "policies": {},
      "checkConstraints": {},
      "isRLSEnabled": false
    },
    "public.generated_documents": {
      "name": "generated_documents",
      "schema": "",
      "columns": {
        "id": {
          "name": "id",
          "type": "uuid",
          "primaryKey": true,
          "notNull": true,
          "default": "gen_random_uuid()"
        },
        "organization_id": {
          "name": "organization_id",
          "type": "uuid",
          "primaryKey": false,
          "notNull": true
        },
        "patient_id": {
          "name": "patient_id",
          "type": "uuid",
          "primaryKey": false,
          "notNull": true
        },
        "visit_id": {
          "name": "visit_id",
          "type": "uuid",
          "primaryKey": false,
          "notNull": false
        },
        "kind": {
          "name": "kind",
          "type": "document_kind",
          "typeSchema": "public",
          "primaryKey": false,
          "notNull": true
        },
        "status": {
          "name": "status",
          "type": "document_status",
          "typeSchema": "public",
          "primaryKey": false,
          "notNull": true,
          "default": "'draft'"
        },
        "title": {
          "name": "title",
          "type": "text",
          "primaryKey": false,
          "notNull": true
        },
        "storage_path": {
          "name": "storage_path",
          "type": "text",
          "primaryKey": false,
          "notNull": false
        },
        "total_amount_rub": {
          "name": "total_amount_rub",
          "type": "integer",
          "primaryKey": false,
          "notNull": false
        },
        "issued_at": {
          "name": "issued_at",
          "type": "timestamp with time zone",
          "primaryKey": false,
          "notNull": false
        },
        "created_at": {
          "name": "created_at",
          "type": "timestamp with time zone",
          "primaryKey": false,
          "notNull": true,
          "default": "now()"
        }
      },
      "indexes": {},
      "foreignKeys": {
        "generated_documents_organization_id_organizations_id_fk": {
          "name": "generated_documents_organization_id_organizations_id_fk",
          "tableFrom": "generated_documents",
          "tableTo": "organizations",
          "columnsFrom": [
            "organization_id"
          ],
          "columnsTo": [
            "id"
          ],
          "onDelete": "no action",
          "onUpdate": "no action"
        },
        "generated_documents_patient_id_patients_id_fk": {
          "name": "generated_documents_patient_id_patients_id_fk",
          "tableFrom": "generated_documents",
          "tableTo": "patients",
          "columnsFrom": [
            "patient_id"
          ],
          "columnsTo": [
            "id"
          ],
          "onDelete": "no action",
          "onUpdate": "no action"
        },
        "generated_documents_visit_id_visits_id_fk": {
          "name": "generated_documents_visit_id_visits_id_fk",
          "tableFrom": "generated_documents",
          "tableTo": "visits",
          "columnsFrom": [
            "visit_id"
          ],
          "columnsTo": [
            "id"
          ],
          "onDelete": "no action",
          "onUpdate": "no action"
        }
      },
      "compositePrimaryKeys": {},
      "uniqueConstraints": {},
      "policies": {},
      "checkConstraints": {},
      "isRLSEnabled": false
    },
    "public.import_batches": {
      "name": "import_batches",
      "schema": "",
      "columns": {
        "id": {
          "name": "id",
          "type": "uuid",
          "primaryKey": true,
          "notNull": true,
          "default": "gen_random_uuid()"
        },
        "organization_id": {
          "name": "organization_id",
          "type": "uuid",
          "primaryKey": false,
          "notNull": true
        },
        "source_name": {
          "name": "source_name",
          "type": "text",
          "primaryKey": false,
          "notNull": true
        },
        "status": {
          "name": "status",
          "type": "text",
          "primaryKey": false,
          "notNull": true
        },
        "created_at": {
          "name": "created_at",
          "type": "timestamp with time zone",
          "primaryKey": false,
          "notNull": true,
          "default": "now()"
        }
      },
      "indexes": {},
      "foreignKeys": {
        "import_batches_organization_id_organizations_id_fk": {
          "name": "import_batches_organization_id_organizations_id_fk",
          "tableFrom": "import_batches",
          "tableTo": "organizations",
          "columnsFrom": [
            "organization_id"
          ],
          "columnsTo": [
            "id"
          ],
          "onDelete": "no action",
          "onUpdate": "no action"
        }
      },
      "compositePrimaryKeys": {},
      "uniqueConstraints": {},
      "policies": {},
      "checkConstraints": {},
      "isRLSEnabled": false
    },
    "public.organizations": {
      "name": "organizations",
      "schema": "",
      "columns": {
        "id": {
          "name": "id",
          "type": "uuid",
          "primaryKey": true,
          "notNull": true,
          "default": "gen_random_uuid()"
        },
        "name": {
          "name": "name",
          "type": "text",
          "primaryKey": false,
          "notNull": true
        },
        "inn": {
          "name": "inn",
          "type": "text",
          "primaryKey": false,
          "notNull": false
        },
        "ogrn": {
          "name": "ogrn",
          "type": "text",
          "primaryKey": false,
          "notNull": false
        },
        "legal_address": {
          "name": "legal_address",
          "type": "text",
          "primaryKey": false,
          "notNull": false
        },
        "medical_license_number": {
          "name": "medical_license_number",
          "type": "text",
          "primaryKey": false,
          "notNull": false
        },
        "medical_license_issued_at": {
          "name": "medical_license_issued_at",
          "type": "text",
          "primaryKey": false,
          "notNull": false
        },
        "created_at": {
          "name": "created_at",
          "type": "timestamp with time zone",
          "primaryKey": false,
          "notNull": true,
          "default": "now()"
        },
        "updated_at": {
          "name": "updated_at",
          "type": "timestamp with time zone",
          "primaryKey": false,
          "notNull": true,
          "default": "now()"
        }
      },
      "indexes": {},
      "foreignKeys": {},
      "compositePrimaryKeys": {},
      "uniqueConstraints": {},
      "policies": {},
      "checkConstraints": {},
      "isRLSEnabled": false
    },
    "public.patient_consents": {
      "name": "patient_consents",
      "schema": "",
      "columns": {
        "id": {
          "name": "id",
          "type": "uuid",
          "primaryKey": true,
          "notNull": true,
          "default": "gen_random_uuid()"
        },
        "organization_id": {
          "name": "organization_id",
          "type": "uuid",
          "primaryKey": false,
          "notNull": true
        },
        "patient_id": {
          "name": "patient_id",
          "type": "uuid",
          "primaryKey": false,
          "notNull": true
        },
        "kind": {
          "name": "kind",
          "type": "text",
          "primaryKey": false,
          "notNull": true
        },
        "granted_at": {
          "name": "granted_at",
          "type": "timestamp with time zone",
          "primaryKey": false,
          "notNull": false
        },
        "revoked_at": {
          "name": "revoked_at",
          "type": "timestamp with time zone",
          "primaryKey": false,
          "notNull": false
        },
        "document_id": {
          "name": "document_id",
          "type": "uuid",
          "primaryKey": false,
          "notNull": false
        }
      },
      "indexes": {},
      "foreignKeys": {
        "patient_consents_organization_id_organizations_id_fk": {
          "name": "patient_consents_organization_id_organizations_id_fk",
          "tableFrom": "patient_consents",
          "tableTo": "organizations",
          "columnsFrom": [
            "organization_id"
          ],
          "columnsTo": [
            "id"
          ],
          "onDelete": "no action",
          "onUpdate": "no action"
        },
        "patient_consents_patient_id_patients_id_fk": {
          "name": "patient_consents_patient_id_patients_id_fk",
          "tableFrom": "patient_consents",
          "tableTo": "patients",
          "columnsFrom": [
            "patient_id"
          ],
          "columnsTo": [
            "id"
          ],
          "onDelete": "no action",
          "onUpdate": "no action"
        }
      },
      "compositePrimaryKeys": {},
      "uniqueConstraints": {},
      "policies": {},
      "checkConstraints": {},
      "isRLSEnabled": false
    },
    "public.patients": {
      "name": "patients",
      "schema": "",
      "columns": {
        "id": {
          "name": "id",
          "type": "uuid",
          "primaryKey": true,
          "notNull": true,
          "default": "gen_random_uuid()"
        },
        "organization_id": {
          "name": "organization_id",
          "type": "uuid",
          "primaryKey": false,
          "notNull": true
        },
        "status": {
          "name": "status",
          "type": "patient_status",
          "typeSchema": "public",
          "primaryKey": false,
          "notNull": true,
          "default": "'active'"
        },
        "full_name": {
          "name": "full_name",
          "type": "text",
          "primaryKey": false,
          "notNull": true
        },
        "birth_date": {
          "name": "birth_date",
          "type": "text",
          "primaryKey": false,
          "notNull": false
        },
        "phone": {
          "name": "phone",
          "type": "text",
          "primaryKey": false,
          "notNull": false
        },
        "email": {
          "name": "email",
          "type": "text",
          "primaryKey": false,
          "notNull": false
        },
        "notes": {
          "name": "notes",
          "type": "text",
          "primaryKey": false,
          "notNull": false
        },
        "created_at": {
          "name": "created_at",
          "type": "timestamp with time zone",
          "primaryKey": false,
          "notNull": true,
          "default": "now()"
        },
        "updated_at": {
          "name": "updated_at",
          "type": "timestamp with time zone",
          "primaryKey": false,
          "notNull": true,
          "default": "now()"
        }
      },
      "indexes": {},
      "foreignKeys": {
        "patients_organization_id_organizations_id_fk": {
          "name": "patients_organization_id_organizations_id_fk",
          "tableFrom": "patients",
          "tableTo": "organizations",
          "columnsFrom": [
            "organization_id"
          ],
          "columnsTo": [
            "id"
          ],
          "onDelete": "no action",
          "onUpdate": "no action"
        }
      },
      "compositePrimaryKeys": {},
      "uniqueConstraints": {},
      "policies": {},
      "checkConstraints": {},
      "isRLSEnabled": false
    },
    "public.payments": {
      "name": "payments",
      "schema": "",
      "columns": {
        "id": {
          "name": "id",
          "type": "uuid",
          "primaryKey": true,
          "notNull": true,
          "default": "gen_random_uuid()"
        },
        "organization_id": {
          "name": "organization_id",
          "type": "uuid",
          "primaryKey": false,
          "notNull": true
        },
        "patient_id": {
          "name": "patient_id",
          "type": "uuid",
          "primaryKey": false,
          "notNull": true
        },
        "visit_id": {
          "name": "visit_id",
          "type": "uuid",
          "primaryKey": false,
          "notNull": false
        },
        "amount_rub": {
          "name": "amount_rub",
          "type": "integer",
          "primaryKey": false,
          "notNull": true
        },
        "method": {
          "name": "method",
          "type": "text",
          "primaryKey": false,
          "notNull": true
        },
        "paid_at": {
          "name": "paid_at",
          "type": "timestamp with time zone",
          "primaryKey": false,
          "notNull": true
        },
        "fiscal_receipt_number": {
          "name": "fiscal_receipt_number",
          "type": "text",
          "primaryKey": false,
          "notNull": false
        }
      },
      "indexes": {},
      "foreignKeys": {
        "payments_organization_id_organizations_id_fk": {
          "name": "payments_organization_id_organizations_id_fk",
          "tableFrom": "payments",
          "tableTo": "organizations",
          "columnsFrom": [
            "organization_id"
          ],
          "columnsTo": [
            "id"
          ],
          "onDelete": "no action",
          "onUpdate": "no action"
        },
        "payments_patient_id_patients_id_fk": {
          "name": "payments_patient_id_patients_id_fk",
          "tableFrom": "payments",
          "tableTo": "patients",
          "columnsFrom": [
            "patient_id"
          ],
          "columnsTo": [
            "id"
          ],
          "onDelete": "no action",
          "onUpdate": "no action"
        },
        "payments_visit_id_visits_id_fk": {
          "name": "payments_visit_id_visits_id_fk",
          "tableFrom": "payments",
          "tableTo": "visits",
          "columnsFrom": [
            "visit_id"
          ],
          "columnsTo": [
            "id"
          ],
          "onDelete": "no action",
          "onUpdate": "no action"
        }
      },
      "compositePrimaryKeys": {},
      "uniqueConstraints": {},
      "policies": {},
      "checkConstraints": {},
      "isRLSEnabled": false
    },
    "public.service_catalog_items": {
      "name": "service_catalog_items",
      "schema": "",
      "columns": {
        "id": {
          "name": "id",
          "type": "uuid",
          "primaryKey": true,
          "notNull": true,
          "default": "gen_random_uuid()"
        },
        "organization_id": {
          "name": "organization_id",
          "type": "uuid",
          "primaryKey": false,
          "notNull": true
        },
        "code": {
          "name": "code",
          "type": "text",
          "primaryKey": false,
          "notNull": true
        },
        "title": {
          "name": "title",
          "type": "text",
          "primaryKey": false,
          "notNull": true
        },
        "price_rub": {
          "name": "price_rub",
          "type": "integer",
          "primaryKey": false,
          "notNull": true
        },
        "tax_deduction_code": {
          "name": "tax_deduction_code",
          "type": "text",
          "primaryKey": false,
          "notNull": false
        },
        "is_active": {
          "name": "is_active",
          "type": "boolean",
          "primaryKey": false,
          "notNull": true,
          "default": true
        }
      },
      "indexes": {},
      "foreignKeys": {
        "service_catalog_items_organization_id_organizations_id_fk": {
          "name": "service_catalog_items_organization_id_organizations_id_fk",
          "tableFrom": "service_catalog_items",
          "tableTo": "organizations",
          "columnsFrom": [
            "organization_id"
          ],
          "columnsTo": [
            "id"
          ],
          "onDelete": "no action",
          "onUpdate": "no action"
        }
      },
      "compositePrimaryKeys": {},
      "uniqueConstraints": {},
      "policies": {},
      "checkConstraints": {},
      "isRLSEnabled": false
    },
    "public.treatment_items": {
      "name": "treatment_items",
      "schema": "",
      "columns": {
        "id": {
          "name": "id",
          "type": "uuid",
          "primaryKey": true,
          "notNull": true,
          "default": "gen_random_uuid()"
        },
        "organization_id": {
          "name": "organization_id",
          "type": "uuid",
          "primaryKey": false,
          "notNull": true
        },
        "visit_id": {
          "name": "visit_id",
          "type": "uuid",
          "primaryKey": false,
          "notNull": true
        },
        "service_id": {
          "name": "service_id",
          "type": "uuid",
          "primaryKey": false,
          "notNull": false
        },
        "tooth_code": {
          "name": "tooth_code",
          "type": "text",
          "primaryKey": false,
          "notNull": false
        },
        "title": {
          "name": "title",
          "type": "text",
          "primaryKey": false,
          "notNull": true
        },
        "quantity": {
          "name": "quantity",
          "type": "numeric(10, 2)",
          "primaryKey": false,
          "notNull": true,
          "default": "'1'"
        },
        "price_rub": {
          "name": "price_rub",
          "type": "integer",
          "primaryKey": false,
          "notNull": true
        }
      },
      "indexes": {},
      "foreignKeys": {
        "treatment_items_organization_id_organizations_id_fk": {
          "name": "treatment_items_organization_id_organizations_id_fk",
          "tableFrom": "treatment_items",
          "tableTo": "organizations",
          "columnsFrom": [
            "organization_id"
          ],
          "columnsTo": [
            "id"
          ],
          "onDelete": "no action",
          "onUpdate": "no action"
        },
        "treatment_items_visit_id_visits_id_fk": {
          "name": "treatment_items_visit_id_visits_id_fk",
          "tableFrom": "treatment_items",
          "tableTo": "visits",
          "columnsFrom": [
            "visit_id"
          ],
          "columnsTo": [
            "id"
          ],
          "onDelete": "no action",
          "onUpdate": "no action"
        },
        "treatment_items_service_id_service_catalog_items_id_fk": {
          "name": "treatment_items_service_id_service_catalog_items_id_fk",
          "tableFrom": "treatment_items",
          "tableTo": "service_catalog_items",
          "columnsFrom": [
            "service_id"
          ],
          "columnsTo": [
            "id"
          ],
          "onDelete": "no action",
          "onUpdate": "no action"
        }
      },
      "compositePrimaryKeys": {},
      "uniqueConstraints": {},
      "policies": {},
      "checkConstraints": {},
      "isRLSEnabled": false
    },
    "public.users": {
      "name": "users",
      "schema": "",
      "columns": {
        "id": {
          "name": "id",
          "type": "uuid",
          "primaryKey": true,
          "notNull": true,
          "default": "gen_random_uuid()"
        },
        "organization_id": {
          "name": "organization_id",
          "type": "uuid",
          "primaryKey": false,
          "notNull": true
        },
        "full_name": {
          "name": "full_name",
          "type": "text",
          "primaryKey": false,
          "notNull": true
        },
        "role": {
          "name": "role",
          "type": "text",
          "primaryKey": false,
          "notNull": true
        },
        "phone": {
          "name": "phone",
          "type": "text",
          "primaryKey": false,
          "notNull": false
        },
        "email": {
          "name": "email",
          "type": "text",
          "primaryKey": false,
          "notNull": false
        },
        "is_active": {
          "name": "is_active",
          "type": "boolean",
          "primaryKey": false,
          "notNull": true,
          "default": true
        },
        "created_at": {
          "name": "created_at",
          "type": "timestamp with time zone",
          "primaryKey": false,
          "notNull": true,
          "default": "now()"
        }
      },
      "indexes": {},
      "foreignKeys": {
        "users_organization_id_organizations_id_fk": {
          "name": "users_organization_id_organizations_id_fk",
          "tableFrom": "users",
          "tableTo": "organizations",
          "columnsFrom": [
            "organization_id"
          ],
          "columnsTo": [
            "id"
          ],
          "onDelete": "no action",
          "onUpdate": "no action"
        }
      },
      "compositePrimaryKeys": {},
      "uniqueConstraints": {},
      "policies": {},
      "checkConstraints": {},
      "isRLSEnabled": false
    },
    "public.visits": {
      "name": "visits",
      "schema": "",
      "columns": {
        "id": {
          "name": "id",
          "type": "uuid",
          "primaryKey": true,
          "notNull": true,
          "default": "gen_random_uuid()"
        },
        "organization_id": {
          "name": "organization_id",
          "type": "uuid",
          "primaryKey": false,
          "notNull": true
        },
        "patient_id": {
          "name": "patient_id",
          "type": "uuid",
          "primaryKey": false,
          "notNull": true
        },
        "appointment_id": {
          "name": "appointment_id",
          "type": "uuid",
          "primaryKey": false,
          "notNull": false
        },
        "status": {
          "name": "status",
          "type": "visit_status",
          "typeSchema": "public",
          "primaryKey": false,
          "notNull": true,
          "default": "'draft'"
        },
        "complaint": {
          "name": "complaint",
          "type": "text",
          "primaryKey": false,
          "notNull": false
        },
        "anamnesis": {
          "name": "anamnesis",
          "type": "text",
          "primaryKey": false,
          "notNull": false
        },
        "objective_status": {
          "name": "objective_status",
          "type": "text",
          "primaryKey": false,
          "notNull": false
        },
        "diagnosis": {
          "name": "diagnosis",
          "type": "text",
          "primaryKey": false,
          "notNull": false
        },
        "treatment_plan": {
          "name": "treatment_plan",
          "type": "text",
          "primaryKey": false,
          "notNull": false
        },
        "doctor_summary": {
          "name": "doctor_summary",
          "type": "text",
          "primaryKey": false,
          "notNull": false
        },
        "signed_at": {
          "name": "signed_at",
          "type": "timestamp with time zone",
          "primaryKey": false,
          "notNull": false
        },
        "created_at": {
          "name": "created_at",
          "type": "timestamp with time zone",
          "primaryKey": false,
          "notNull": true,
          "default": "now()"
        },
        "updated_at": {
          "name": "updated_at",
          "type": "timestamp with time zone",
          "primaryKey": false,
          "notNull": true,
          "default": "now()"
        }
      },
      "indexes": {},
      "foreignKeys": {
        "visits_organization_id_organizations_id_fk": {
          "name": "visits_organization_id_organizations_id_fk",
          "tableFrom": "visits",
          "tableTo": "organizations",
          "columnsFrom": [
            "organization_id"
          ],
          "columnsTo": [
            "id"
          ],
          "onDelete": "no action",
          "onUpdate": "no action"
        },
        "visits_patient_id_patients_id_fk": {
          "name": "visits_patient_id_patients_id_fk",
          "tableFrom": "visits",
          "tableTo": "patients",
          "columnsFrom": [
            "patient_id"
          ],
          "columnsTo": [
            "id"
          ],
          "onDelete": "no action",
          "onUpdate": "no action"
        },
        "visits_appointment_id_appointments_id_fk": {
          "name": "visits_appointment_id_appointments_id_fk",
          "tableFrom": "visits",
          "tableTo": "appointments",
          "columnsFrom": [
            "appointment_id"
          ],
          "columnsTo": [
            "id"
          ],
          "onDelete": "no action",
          "onUpdate": "no action"
        }
      },
      "compositePrimaryKeys": {},
      "uniqueConstraints": {},
      "policies": {},
      "checkConstraints": {},
      "isRLSEnabled": false
    }
  },
  "enums": {
    "public.ai_job_kind": {
      "name": "ai_job_kind",
      "schema": "public",
      "values": [
        "voice_transcription",
        "visit_note_draft",
        "image_summary",
        "document_draft"
      ]
    },
    "public.ai_job_status": {
      "name": "ai_job_status",
      "schema": "public",
      "values": [
        "queued",
        "running",
        "needs_review",
        "accepted",
        "rejected",
        "failed"
      ]
    },
    "public.appointment_status": {
      "name": "appointment_status",
      "schema": "public",
      "values": [
        "planned",
        "confirmed",
        "arrived",
        "in_treatment",
        "completed",
        "cancelled",
        "no_show"
      ]
    },
    "public.document_kind": {
      "name": "document_kind",
      "schema": "public",
      "values": [
        "paid_medical_services_contract",
        "completed_works_act",
        "tax_deduction_certificate",
        "informed_consent",
        "treatment_plan"
      ]
    },
    "public.document_status": {
      "name": "document_status",
      "schema": "public",
      "values": [
        "draft",
        "issued",
        "voided"
      ]
    },
    "public.patient_status": {
      "name": "patient_status",
      "schema": "public",
      "values": [
        "active",
        "archived"
      ]
    },
    "public.visit_status": {
      "name": "visit_status",
      "schema": "public",
      "values": [
        "draft",
        "signed",
        "voided"
      ]
    }
  },
  "schemas": {},
  "sequences": {},
  "roles": {},
  "policies": {},
  "views": {},
  "_meta": {
    "columns": {},
    "schemas": {},
    "tables": {}
  }
}